Metadata-Version: 2.1
Name: graphene-django-optimizer-patch
Version: 0.8.0.2
Summary: Optimize database access inside graphene queries.
Home-page: https://github.com/gabrielsebag/graphene-django-optimizer
Author: Gabriel Sebag
Author-email: hello@gabrielsebag.com
License: MIT
Keywords: graphene django optimizer optimize graphql query prefetch select related
Platform: UNKNOWN
Classifier: Development Status :: 4 - Beta
Classifier: Environment :: Web Environment
Classifier: Intended Audience :: Developers
Classifier: License :: OSI Approved :: MIT License
Classifier: Operating System :: OS Independent
Classifier: Programming Language :: Python
Classifier: Programming Language :: Python :: 2.7
Classifier: Programming Language :: Python :: 3
Classifier: Programming Language :: Python :: 3.5
Classifier: Programming Language :: Python :: 3.6
Classifier: Programming Language :: Python :: 3.7
Classifier: Programming Language :: Python :: 3.8
Classifier: Framework :: Django
Classifier: Framework :: Django :: 1.11
Classifier: Framework :: Django :: 2.0
Classifier: Framework :: Django :: 2.1
Classifier: Framework :: Django :: 2.2
Classifier: Framework :: Django :: 3.0
Classifier: Framework :: Django :: 3.1
License-File: LICENSE
